rabbitmq_flask/ExchangeParams.py
rabbitmq_flask/ExchangeType.py
rabbitmq_flask/QueueParams.py
rabbitmq_flask/RabbitConsumerMiddleware.py
rabbitmq_flask/RabbitMQ.py
rabbitmq_flask/__init__.py
rabbitmq_flask-1.0.3.dist-info/LICENSE
rabbitmq_flask-1.0.3.dist-info/METADATA
rabbitmq_flask-1.0.3.dist-info/WHEEL
rabbitmq_flask-1.0.3.dist-info/top_level.txt
rabbitmq_flask-1.0.3.dist-info/RECORD
